[{"ID":"fotboll10","name":"Stockholm FC","type":"b22samer","company":"","location":"Stockholm","category":"","size":35,"cost":50000,"auxdata":""},{"ID":"fotboll11","name":"Norrköping FC","type":"b22samer","company":"","location":"Norrköping","category":"","size":25,"cost":30000,"auxdata":""},{"ID":"fotboll12","name":"Göteborg FC","type":"b22samer","company":"","location":"Göteborg","category":"","size":30,"cost":45000,"auxdata":""},{"ID":"fotboll13","name":"Örebro FC","type":"b22samer","company":"","location":"Örebro","category":"","size":23,"cost":35000,"auxdata":""},{"ID":"fotboll14","name":"Linköping FC","type":"b22samer","company":"","location":"Linköping","category":"","size":15,"cost":20000,"auxdata":""}]